{
    "3d-printing": 1,
    "android": 1,
    "architecture": 1,
    "arduino": 1,
    "arm": 1,
    "awesome": 1,
    "c": 3,
    "c-plus-plus": 1,
    "china": 1,
    "cobalt-strike": 1,
    "cortex-a": 1,
    "cortex-m": 1,
    "cross-platform": 1,
    "cross-platform-gui": 1,
    "directshow": 1,
    "display": 1,
    "embedded": 1,
    "embedded-systems": 1,
    "esp-idf": 1,
    "esp32": 1,
    "facebook-live": 1,
    "ffmpeg": 1,
    "game-capture": 1,
    "graphical-user-interface": 1,
    "graphics-library": 1,
    "gui": 1,
    "gui-framework": 1,
    "gui-toolkit": 1,
    "harmonyos": 1,
    "huawei": 1,
    "ids": 1,
    "ios": 1,
    "iot": 2,
    "iot-platform": 1,
    "ips": 1,
    "kernel": 2,
    "lede": 1,
    "linux": 2,
    "live-streaming": 1,
    "lua": 1,
    "lvgl": 1,
    "macos": 1,
    "microcontroller": 1,
    "mips": 1,
    "motor": 1,
    "motor-controller": 1,
    "network-monitoring": 1,
    "nsm": 1,
    "openwrt": 2,
    "openwrt-feed": 1,
    "openwrt-package": 2,
    "openwrt-shadowsocksr-libev-full": 1,
    "openwrt-zh-cn": 1,
    "operating-system": 1,
    "os": 1,
    "platformio": 1,
    "redteam": 1,
    "risc-v": 1,
    "rtos": 1,
    "screen-capture": 1,
    "security": 1,
    "tft": 1,
    "twitch-tv": 1,
    "uwp": 1,
    "video-recording": 1,
    "videogames": 1,
    "windows": 1,
    "youtube-live": 1
}
