{
    "abp": 1,
    "adobe-xd": 1,
    "android": 1,
    "angular": 1,
    "api-gateway": 1,
    "architecture": 4,
    "arm": 1,
    "asp": 1,
    "aspnet": 1,
    "aspnet-core": 1,
    "aspnetcore": 2,
    "azure": 3,
    "azure-cosmos": 1,
    "azure-devops": 1,
    "azure-functions": 1,
    "azure-sdk": 1,
    "background": 1,
    "bluetooth-low-energy": 1,
    "blur": 1,
    "bot-framework": 1,
    "bots": 1,
    "c-sharp": 2,
    "capture": 1,
    "chocolatey": 1,
    "clean-architecture": 4,
    "clean-code": 2,
    "cleanarchitecture": 1,
    "client-xamarin": 1,
    "component": 1,
    "consul": 1,
    "coronavirus": 1,
    "coronavirus-tracker": 1,
    "coronavirus-tracking": 1,
    "country": 1,
    "covid": 1,
    "covid-19": 1,
    "cqrs": 2,
    "craftsmanship": 1,
    "csharp": 7,
    "curses": 1,
    "ddd": 1,
    "ddd-architecture": 2,
    "ddd-cqrs": 1,
    "ddd-example": 1,
    "deep-learning": 1,
    "deep-reinforcement-learning": 1,
    "design-patterns": 2,
    "design-systems": 1,
    "docker": 1,
    "docs": 1,
    "domain-driven-design": 3,
    "dotnet": 6,
    "dotnet-core": 6,
    "dotnet5": 1,
    "dotnetcore": 2,
    "effect": 1,
    "elk": 1,
    "emulation": 1,
    "emulator": 1,
    "entity-framework-core": 2,
    "entityframeworkcore": 1,
    "event-sourcing": 2,
    "eventbus": 1,
    "eventsourcing": 1,
    "evolutionary-architecture": 1,
    "exposure-notification": 1,
    "framework": 1,
    "gif": 1,
    "grayscale": 1,
    "gui": 1,
    "hexagonal-architecture": 1,
    "ios-ibeacon": 1,
    "javascript": 1,
    "jellyfin": 1,
    "keystrokes": 1,
    "language-design": 1,
    "luis": 1,
    "luis-ai": 1,
    "mediatr": 1,
    "message-broker": 1,
    "micro-service": 1,
    "microservice": 1,
    "microservices": 1,
    "microservices-architecture": 1,
    "microsoft": 2,
    "microsoft-azure-powershell": 1,
    "microsoft-congnitive-services": 1,
    "modular": 1,
    "modular-applications": 1,
    "modularity": 1,
    "monolith": 1,
    "multi-tenancy": 1,
    "mvvm": 1,
    "netcore": 1,
    "netcore3": 1,
    "neural-networks": 1,
    "onion-architecture": 1,
    "outbox": 1,
    "outbox-database": 1,
    "powershell": 1,
    "prism": 1,
    "qnamaker": 1,
    "rabbitmq": 1,
    "record": 1,
    "recording": 1,
    "region-capture": 1,
    "reinforcement-learning": 1,
    "rest": 1,
    "rest-api": 1,
    "roslyn": 1,
    "saga": 1,
    "saga-transactions": 1,
    "screen-capture": 1,
    "screen-recorder": 1,
    "screencast": 1,
    "screenshot": 1,
    "sdk": 1,
    "sepia": 1,
    "shader": 1,
    "shadowsocksr": 1,
    "software-architecture": 1,
    "solid-principles": 1,
    "swagger": 1,
    "switch": 1,
    "tdd": 1,
    "template": 1,
    "terminal": 1,
    "tester": 1,
    "toolkit": 1,
    "typescript": 1,
    "ugui": 1,
    "ui": 1,
    "unity": 2,
    "unity3d": 2,
    "visual-basic": 1,
    "visual-studio": 3,
    "vsix": 1,
    "webapi": 1,
    "webcam": 1,
    "windows": 1,
    "workflow": 1,
    "workflow-engine": 1,
    "wpf": 3,
    "xamarin-forms": 1,
    "xamarin-studio": 1,
    "yeoman": 1
}
