{
    "3d-mapping": 1,
    "adalight": 1,
    "ai-framework": 1,
    "algorithm": 1,
    "ambilight": 1,
    "arm": 1,
    "arm-neon": 1,
    "artificial-intelligence": 1,
    "autograd": 1,
    "bar": 1,
    "boost": 1,
    "bspwm": 1,
    "c": 2,
    "c-plus-plus": 5,
    "c-sharp": 1,
    "capture": 1,
    "chrome": 1,
    "cnn": 1,
    "computer-vision": 3,
    "cpp": 3,
    "cpp11": 1,
    "cross-platform": 1,
    "css": 1,
    "data-structures": 1,
    "database": 1,
    "deep-learning": 3,
    "dnn": 1,
    "doris": 1,
    "effects": 1,
    "electron": 1,
    "fisheye": 1,
    "flatbuffers": 1,
    "geospatial-data": 1,
    "go": 1,
    "gpu": 1,
    "grpc": 1,
    "hardware-acceleration": 1,
    "header-only": 1,
    "html": 1,
    "hue": 1,
    "hyperion": 1,
    "i3wm": 1,
    "image-processing": 1,
    "interview": 1,
    "interview-practice": 1,
    "interview-preparation": 1,
    "interview-questions": 1,
    "interviews": 1,
    "java": 1,
    "javascript": 2,
    "json-parser": 1,
    "leetcode": 1,
    "lidar-inertial": 1,
    "lidar-odometry": 1,
    "lidar-slam": 1,
    "linux": 1,
    "loam-velodyne": 1,
    "logging": 1,
    "machine-learning": 3,
    "marshalling": 2,
    "mmap": 1,
    "mood": 1,
    "neural-network": 1,
    "neural-networks": 1,
    "nodejs": 1,
    "numpy": 1,
    "onnx": 2,
    "opencv": 1,
    "operating-system": 1,
    "option-parser": 1,
    "ouster": 1,
    "ouster-slam": 1,
    "panorama": 1,
    "pcl": 1,
    "point-cloud": 1,
    "pointcloud": 1,
    "polybar": 1,
    "positional-arguments": 1,
    "protobuf": 2,
    "protobuf-runtime": 1,
    "protoc": 1,
    "protocol-buffers": 1,
    "protocol-compiler": 1,
    "python": 2,
    "pytorch": 2,
    "raspberry": 1,
    "raster": 1,
    "robotics": 1,
    "rpc": 2,
    "rpi": 1,
    "rust": 1,
    "scikit-learn": 1,
    "serialization": 2,
    "serialization-library": 1,
    "slam": 2,
    "stl": 1,
    "tensor": 1,
    "tensorflow": 2,
    "typescript": 1,
    "v8": 1,
    "vector": 1,
    "velodyne": 1,
    "velodyne-slam": 1,
    "visual-odometry": 1,
    "visual-slam": 1,
    "vr": 1,
    "vslam": 1,
    "window-manager": 1,
    "workaround": 1,
    "ws281x": 1,
    "zero-copy": 1
}
