{
    "1080p": 1,
    "agent": 1,
    "algorithm-challenges": 1,
    "algorithms": 1,
    "algorithms-datastructures": 1,
    "algorithms-implemented": 1,
    "alibaba": 2,
    "android": 2,
    "antlr": 1,
    "antlr4": 1,
    "apache-shiro": 1,
    "apm": 2,
    "appsec": 1,
    "arthas": 1,
    "awesome-list": 1,
    "azkaban": 1,
    "big-data": 1,
    "bigdata": 1,
    "bootstrap": 1,
    "bulkhead": 1,
    "circuitbreaker": 1,
    "classloader": 1,
    "config": 1,
    "configuration-management": 1,
    "cpp": 1,
    "csharp": 1,
    "dapper": 1,
    "dast": 1,
    "design-patterns": 1,
    "diagnosis": 1,
    "distributed": 1,
    "distributed-configuration": 1,
    "distributed-tracing": 1,
    "dns": 1,
    "docker": 1,
    "docker-composer": 1,
    "download-videos": 1,
    "dubbo": 2,
    "elasticsearch": 1,
    "excel": 1,
    "exoplayer": 1,
    "fastdfs": 1,
    "flume": 1,
    "framework": 1,
    "golang": 1,
    "grammar": 1,
    "hadoop": 1,
    "hbase": 1,
    "hdfs": 1,
    "hive": 1,
    "implementation": 1,
    "interview": 1,
    "interview-questions": 1,
    "istio": 1,
    "java": 11,
    "javascript": 1,
    "jdbctemplate": 1,
    "jvm": 1,
    "jxl": 1,
    "kafka": 2,
    "kubernetes": 1,
    "language-recognition": 1,
    "learning": 1,
    "log4j": 1,
    "mapreduce": 1,
    "mediaplayer": 1,
    "metrics": 2,
    "microservices": 1,
    "mongodb": 1,
    "monitoring": 1,
    "mybatis": 2,
    "nacos": 1,
    "newpipe": 1,
    "observability": 1,
    "oom": 1,
    "owasp": 1,
    "owasp-zap": 1,
    "parse": 1,
    "parser-generator": 1,
    "parsing": 1,
    "phoenix": 1,
    "poi": 1,
    "principles": 1,
    "python": 1,
    "rabbitmq": 1,
    "rate-limiter": 1,
    "realtime": 1,
    "redis": 2,
    "reference": 1,
    "resilience": 1,
    "retry": 1,
    "rocketmq": 1,
    "scala": 2,
    "scheduler": 1,
    "search": 1,
    "search-engine": 1,
    "security": 1,
    "security-scanner": 1,
    "service-discovery": 1,
    "service-mesh": 2,
    "shiro": 2,
    "skywalking": 1,
    "snippets": 1,
    "snippets-collection": 1,
    "snippets-library": 1,
    "sort": 1,
    "sorting-algorithms": 1,
    "spark": 1,
    "spring": 3,
    "spring-boot": 5,
    "spring-boot-examples": 1,
    "spring-boot-learning": 1,
    "spring-boot-mail": 1,
    "spring-boot-mongodb": 1,
    "spring-boot-upload-file": 1,
    "spring-boot2": 1,
    "spring-cloud": 4,
    "spring-data-jpa": 2,
    "spring-security": 1,
    "springboot": 2,
    "springboot-shiro": 1,
    "springcloud": 1,
    "sqoop": 1,
    "storm": 1,
    "swift": 1,
    "thymeleaf": 1,
    "trace": 1,
    "tracing": 1,
    "translation": 1,
    "trouble-shooting": 1,
    "video": 1,
    "watch": 1,
    "wiki": 1,
    "xls": 1,
    "xlsx": 1,
    "yarn": 1,
    "youtube-video": 1,
    "zap": 1,
    "zap-development": 1,
    "zaproxy": 1,
    "zookeeper": 1
}
