{
    "3d": 1,
    "3d-graphics": 1,
    "3d-printing": 1,
    "algorithm": 1,
    "algorithms": 1,
    "animated-sprites": 1,
    "animation": 1,
    "arduino": 1,
    "argon2": 1,
    "aseprite": 1,
    "atmel": 1,
    "autograd": 1,
    "avr": 1,
    "baekjoon": 1,
    "baekjoon-algorithm": 1,
    "baekjoon-online-judge": 1,
    "baekjoon-online-judge-solution": 1,
    "baekjoon-solutions": 1,
    "bfs": 1,
    "bitcoin": 1,
    "bittorrent": 1,
    "bittorrent-client": 1,
    "c-plus-plus": 6,
    "cataclysm": 1,
    "cmd": 1,
    "coding-test": 1,
    "command-line": 1,
    "computer-graphics": 1,
    "console": 1,
    "cpp": 4,
    "cpp11": 1,
    "cpuminer": 1,
    "crossplatform": 1,
    "cryptocurrency": 2,
    "cryptography": 1,
    "cryptonight": 1,
    "d3d11": 1,
    "d3d9": 1,
    "data-structure": 1,
    "deep-learning": 1,
    "disjoint-set": 1,
    "draw": 1,
    "drone": 1,
    "dxbc": 1,
    "emulation": 2,
    "emulator": 2,
    "engine": 1,
    "esp32": 2,
    "esp8266": 1,
    "firmware": 1,
    "fpv": 1,
    "fun": 1,
    "game": 1,
    "game-development": 1,
    "game-engine": 1,
    "gamecube": 1,
    "gamedev": 1,
    "gaming": 1,
    "gif": 1,
    "godot": 1,
    "godotengine": 1,
    "gpu": 1,
    "graphics": 2,
    "hacktoberfest": 1,
    "images": 1,
    "interview-practice": 1,
    "interview-preparation": 1,
    "interview-questions": 1,
    "learning": 1,
    "leetcode": 1,
    "leetcode-cpp": 1,
    "leetcode-python": 1,
    "leetcode-solutions": 1,
    "linux": 2,
    "lora": 1,
    "machine-learning": 1,
    "math": 1,
    "messenger": 1,
    "miner": 1,
    "mmorpg": 1,
    "modern-cpp": 1,
    "monero": 1,
    "multi-platform": 3,
    "multiplayer": 1,
    "neural-network": 1,
    "numpy": 1,
    "open-source": 1,
    "opengl": 1,
    "p2p": 1,
    "picture": 1,
    "pixel-art": 1,
    "pixel-editor": 1,
    "pixels": 1,
    "pointer": 1,
    "problem-solving": 1,
    "problems": 1,
    "proton": 1,
    "python": 2,
    "quadcopter": 1,
    "randomx": 1,
    "rasterizer": 1,
    "rc": 1,
    "remote-control": 1,
    "rendering": 1,
    "rendering-engine": 1,
    "rendering-pipeline": 1,
    "reprap": 1,
    "shaders": 1,
    "software-rendering": 1,
    "spir-v": 1,
    "sprites": 1,
    "spritesheet": 1,
    "stm32": 1,
    "stmicro": 1,
    "switch": 1,
    "sx1276": 1,
    "sx1280": 1,
    "telegram": 1,
    "telegram-desktop": 1,
    "telegram-solution": 1,
    "tensor": 1,
    "terminal": 1,
    "tile-editor": 1,
    "tilemap-editor": 1,
    "torrent": 1,
    "torrent-client": 1,
    "trie": 1,
    "trinitycore": 1,
    "tutorial": 1,
    "vulkan": 1,
    "wii": 1,
    "windows-console": 1,
    "windows-terminal": 1,
    "wine": 1,
    "wow": 1,
    "wsl": 1,
    "xmr": 1,
    "xmrig": 1,
    "zombies": 1
}
