{
    "actor": 1,
    "ai": 1,
    "algorithms": 1,
    "aliilapro": 1,
    "android": 1,
    "ant-design": 1,
    "ant-design-blazor": 1,
    "antd": 1,
    "anycpu": 1,
    "api": 1,
    "asp-net-core": 1,
    "aspnet-core": 1,
    "aspnet-product": 1,
    "aspnetcore": 2,
    "avalonia": 1,
    "azure": 1,
    "azure-functions": 1,
    "azure-sdk": 1,
    "beatmap-parser": 1,
    "bepinex": 1,
    "bing-search": 1,
    "bitcoin": 1,
    "blazor": 1,
    "blazor-components": 1,
    "blazor-server": 1,
    "blazor-webassembly": 1,
    "booster": 1,
    "bot": 2,
    "broker": 1,
    "c-sharp": 5,
    "chart": 1,
    "cloudflare": 1,
    "column-series": 1,
    "communication": 1,
    "component": 1,
    "computer-vision": 1,
    "cross-platform": 1,
    "csharp": 5,
    "custom-vision": 1,
    "database": 1,
    "discord": 1,
    "discord-api": 1,
    "discord-net": 1,
    "dnn": 1,
    "dns": 1,
    "dotnet": 3,
    "dotnet-core": 2,
    "dotnet-framework": 1,
    "dotnet-standard": 1,
    "download": 1,
    "effects": 1,
    "entity-framework": 1,
    "framework": 1,
    "game": 1,
    "game-development": 1,
    "game-engine": 1,
    "hacktoberfest": 7,
    "html5": 1,
    "il2cpp": 1,
    "image-classification": 1,
    "iot": 2,
    "iot-framework": 1,
    "iot-platform": 1,
    "javascript": 1,
    "language-learning": 1,
    "line-series": 1,
    "linux": 1,
    "luis": 1,
    "macos": 1,
    "macros": 1,
    "microsoft": 1,
    "mod-loader": 1,
    "modding": 1,
    "modloader": 1,
    "mono": 2,
    "mp3": 1,
    "mp4": 1,
    "mqtt": 1,
    "mqtt-broker": 1,
    "mqtt-client": 1,
    "mqtt-protocol": 1,
    "mqtt-server": 1,
    "mvvm": 1,
    "net": 1,
    "netcore": 3,
    "netframework": 1,
    "nuget": 1,
    "object-detection": 1,
    "ocr": 1,
    "orm": 1,
    "osu": 1,
    "particle": 1,
    "particle-system": 1,
    "patcher": 1,
    "payment-processor": 1,
    "playlist": 1,
    "python": 1,
    "redis": 1,
    "redis-client": 1,
    "redteam": 1,
    "rhythm": 1,
    "roslyn": 2,
    "script": 1,
    "server": 1,
    "skia": 1,
    "skiasharp": 1,
    "steam": 1,
    "swagger": 1,
    "tcp": 1,
    "terraria": 1,
    "terraria-modding-api": 1,
    "tls": 1,
    "tml": 1,
    "tmodloader": 1,
    "translation": 1,
    "ugui": 1,
    "ui": 1,
    "unity": 4,
    "unity-mono": 1,
    "unity3d": 3,
    "unity3d-framework": 1,
    "unlimited": 1,
    "uno": 2,
    "uno-platform": 1,
    "uwp": 3,
    "video": 1,
    "visual-basic": 1,
    "visual-studio": 1,
    "vpn": 1,
    "warp": 1,
    "warp-plus": 1,
    "wasm": 2,
    "webassembly": 2,
    "webm": 1,
    "windows": 1,
    "winforms": 1,
    "winui": 2,
    "winui3": 1,
    "wpf": 1,
    "xamarin": 3,
    "xamarin-forms": 1,
    "xaml": 1,
    "xna": 1,
    "xna-framework": 1,
    "youtube": 1
}
