{
    "ai-framework": 1,
    "algorithm": 1,
    "algorithm-competitions": 1,
    "algorithms": 1,
    "algorithms-implemented": 1,
    "analytics": 1,
    "android": 1,
    "anticensorship": 1,
    "antisurveillance": 1,
    "arducopter": 1,
    "ardupilot": 1,
    "arduplane": 1,
    "ardurover": 1,
    "ardusub": 1,
    "audio-processing": 1,
    "autopilot": 1,
    "auv": 1,
    "big-data": 1,
    "brpc": 1,
    "bson": 1,
    "bypass-gfw": 1,
    "c": 1,
    "c-plus-plus": 5,
    "c-plus-plus-11": 1,
    "c-plus-plus-14": 1,
    "c-plus-plus-17": 1,
    "c-plus-plus-20": 1,
    "c-sharp": 1,
    "calculator": 1,
    "cbor": 1,
    "censorship-circumvention": 1,
    "china": 1,
    "chrome": 1,
    "clickhouse": 1,
    "computer-vision": 2,
    "concurrent-programming": 1,
    "copter": 1,
    "cpp": 1,
    "cross-platform": 1,
    "css": 1,
    "cuda": 1,
    "cuda-programming": 1,
    "data-structures": 1,
    "dbms": 1,
    "deep-learning": 5,
    "deep-neural-networks": 1,
    "differentiable-programming": 1,
    "distributed": 1,
    "distributed-database": 1,
    "drone": 1,
    "dronekit": 1,
    "eastl": 1,
    "electron": 1,
    "flatbuffers": 1,
    "framework": 1,
    "game-development": 1,
    "game-engine": 1,
    "gamedev": 1,
    "games": 1,
    "gfw": 1,
    "go": 1,
    "godot": 1,
    "godotengine": 1,
    "gpgpu": 1,
    "gpu-programming": 2,
    "graph-based": 1,
    "graph-framework": 1,
    "graphics": 1,
    "grpc": 1,
    "hardware-acceleration": 1,
    "header-only": 1,
    "heterogeneous-parallel-programming": 1,
    "high-performance-computing": 1,
    "html": 1,
    "image-processing": 1,
    "inference": 2,
    "inference-engine": 1,
    "interview-preparation": 1,
    "interview-questions": 1,
    "java": 1,
    "javascript": 2,
    "json": 1,
    "json-diff": 1,
    "json-merge-patch": 1,
    "json-parser": 2,
    "json-patch": 1,
    "json-pointer": 1,
    "json-serialization": 1,
    "machine-learning": 3,
    "marshalling": 2,
    "mavlink": 1,
    "mediapipe": 1,
    "messagepack": 1,
    "ml": 1,
    "mmap": 1,
    "mobile-development": 1,
    "modern-cpp": 1,
    "mpp": 1,
    "msgpack": 1,
    "multi-platform": 1,
    "multi-threading": 1,
    "multicore-programming": 1,
    "multithreading": 1,
    "neural-network": 1,
    "neural-networks": 1,
    "nodejs": 1,
    "olap": 1,
    "onnx": 1,
    "open-source": 1,
    "opencv": 1,
    "openvino": 1,
    "parallel-computing": 1,
    "parallel-programming": 1,
    "perception": 1,
    "performance": 1,
    "pipeline-framework": 1,
    "plane": 1,
    "protobuf": 2,
    "protobuf-runtime": 1,
    "protoc": 1,
    "protocol-buffers": 1,
    "protocol-compiler": 1,
    "python": 2,
    "pytorch": 1,
    "rfc-6901": 1,
    "rfc-6902": 1,
    "rfc-7049": 1,
    "rfc-7159": 1,
    "rfc-8259": 1,
    "robotics": 1,
    "ros": 1,
    "rov": 1,
    "rover": 1,
    "rpc": 2,
    "rust": 1,
    "scikit-learn": 1,
    "search": 1,
    "serialization": 2,
    "serialization-library": 1,
    "sort": 1,
    "sparse-computing": 1,
    "sql": 1,
    "stl": 1,
    "stl-containers": 1,
    "stream-processing": 1,
    "sub": 1,
    "taskparallelism": 1,
    "tensorflow": 2,
    "threadpool": 1,
    "trojan": 1,
    "typescript": 1,
    "uas": 1,
    "uav": 1,
    "ubjson": 1,
    "ugv": 1,
    "v8": 1,
    "video-processing": 1,
    "work-stealing": 1,
    "zero-copy": 1
}
