{
    "aarch64": 1,
    "abstract-algebra": 1,
    "akka": 1,
    "alamofire": 1,
    "algorithm-challenges": 1,
    "algorithms": 1,
    "algorithms-datastructures": 1,
    "algorithms-implemented": 1,
    "api-testing": 1,
    "arm": 1,
    "arm64": 1,
    "avx2": 1,
    "awesome-list": 1,
    "beginner-friendly": 1,
    "best-practices": 1,
    "bigdata": 1,
    "blockchain": 1,
    "bundler": 1,
    "carthage": 1,
    "category-theory": 1,
    "certificate-pinning": 1,
    "chai": 1,
    "clang-cl": 1,
    "clang6": 1,
    "cli": 1,
    "client": 1,
    "cocoapods": 1,
    "code": 1,
    "command-line": 1,
    "compiler": 1,
    "connected-vehicles": 1,
    "continuous-testing": 1,
    "cpp11": 1,
    "cpp17": 1,
    "cron": 1,
    "css": 1,
    "database": 1,
    "deep-learning": 2,
    "deep-neural-networks": 1,
    "design-patterns": 1,
    "distributed": 2,
    "documentation": 1,
    "es6": 1,
    "eslint": 1,
    "express": 1,
    "expressjs": 1,
    "flavortown": 1,
    "full-stack": 1,
    "functional-programming": 1,
    "gcc-compiler": 1,
    "gcc7": 1,
    "gcc8": 1,
    "gcc9": 1,
    "generative-model": 1,
    "git": 1,
    "hpc": 1,
    "html": 1,
    "httpurlresponse": 1,
    "image-animation": 1,
    "implementation": 1,
    "industrial-iot": 1,
    "interview": 1,
    "interview-questions": 1,
    "iot": 1,
    "java": 4,
    "javascript": 3,
    "jest": 1,
    "jmeter": 1,
    "json": 1,
    "json-parser": 1,
    "julia": 1,
    "julia-language": 1,
    "kotlin": 1,
    "kotlin-multiplatform": 1,
    "linter": 1,
    "machine-learning": 2,
    "machine-learning-algorithms": 1,
    "mapreduce": 1,
    "microservices": 1,
    "mingw-w64": 1,
    "mirai": 1,
    "ml": 1,
    "mocha": 1,
    "monitoring": 1,
    "motion-retargeting": 1,
    "neon": 1,
    "networking": 1,
    "neural-network": 1,
    "node": 1,
    "node-js": 1,
    "nodejs": 1,
    "nodejs-development": 1,
    "npm": 1,
    "numerical": 1,
    "open-source": 1,
    "parameter-encoding": 1,
    "parity": 1,
    "performance-testing": 1,
    "polkadot": 1,
    "postman": 1,
    "principles": 1,
    "programming-language": 1,
    "public-key-pinning": 1,
    "react": 1,
    "reference": 1,
    "request": 1,
    "response": 1,
    "rest": 1,
    "rust": 3,
    "rustlings": 1,
    "scala": 1,
    "scheduler": 1,
    "science": 1,
    "scientific": 1,
    "search": 1,
    "shell": 1,
    "simd": 1,
    "snippets": 1,
    "snippets-collection": 1,
    "snippets-library": 1,
    "sort": 1,
    "sorting-algorithms": 1,
    "sse42": 1,
    "statistical-learning-method": 1,
    "style-guide": 1,
    "styleguide": 1,
    "substrate": 1,
    "swift": 1,
    "swift-package-manager": 1,
    "syntax-highlighting": 1,
    "terminal": 1,
    "test-automation": 1,
    "testcase": 1,
    "testing": 2,
    "testlink": 1,
    "testlink-alternative": 1,
    "time-series": 1,
    "tool": 1,
    "types": 1,
    "typescript": 1,
    "urlrequest": 1,
    "urlsession": 1,
    "vs2017": 1,
    "vs2019": 1,
    "website": 1,
    "wiki": 1,
    "workflow": 1,
    "xcode": 1,
    "zio": 1
}
