{
    "active-record": 1,
    "admin-dashboard": 1,
    "admin-panels": 1,
    "amazon-cognito": 1,
    "analytics": 1,
    "angular": 3,
    "angular-components": 1,
    "angular-directives": 1,
    "angular-ui-components": 1,
    "angular11": 1,
    "animation-library": 1,
    "ant": 1,
    "ant-design": 1,
    "antd": 1,
    "antv": 1,
    "app-builder": 1,
    "automation": 1,
    "aws": 1,
    "aws-amplify": 1,
    "aws-apigateway": 1,
    "aws-cognito": 1,
    "aws-mobile": 1,
    "aws-mobilehub": 1,
    "aws-s3": 1,
    "azure": 1,
    "browser-ide": 1,
    "chart": 1,
    "cloud": 1,
    "cloud-service": 1,
    "cockroachdb": 1,
    "cognito": 1,
    "collaboration": 1,
    "crud": 1,
    "css": 1,
    "custom-internal": 1,
    "cypress": 1,
    "dag": 1,
    "data-analysis": 1,
    "data-mapper": 1,
    "data-science": 1,
    "data-visualization": 1,
    "database": 1,
    "deep-learning": 1,
    "design-system": 1,
    "design-systems": 1,
    "dev-tools": 1,
    "developer-tools": 2,
    "development-environment": 1,
    "diagram": 1,
    "diagramming": 1,
    "diagrams": 1,
    "dom": 1,
    "drawing": 1,
    "editor": 1,
    "electron": 2,
    "enterprise": 1,
    "erd": 1,
    "erdiagram": 1,
    "firebase": 1,
    "firebase-auth": 1,
    "firebase-authentication": 1,
    "firebase-cloud-messaging": 1,
    "firebase-database": 1,
    "firebase-db": 1,
    "firebase-messaging": 1,
    "firebase-realtime-database": 1,
    "firebase-storage": 1,
    "flowchart": 1,
    "framework": 1,
    "frontend": 1,
    "geist": 1,
    "geist-ui": 1,
    "graph": 1,
    "graph-editor": 1,
    "hacktoberfest": 1,
    "headless-chrome": 1,
    "html": 1,
    "html5": 1,
    "hyper": 1,
    "ide": 1,
    "internal-tools": 1,
    "ivy": 1,
    "java": 1,
    "javascript": 8,
    "javascript-diagramming-library": 1,
    "javascript-framework": 1,
    "layout": 1,
    "linux": 1,
    "low-code": 1,
    "machine-learning": 1,
    "macos": 1,
    "mariadb": 1,
    "metrics": 1,
    "microservices": 1,
    "microsoft": 2,
    "mobile-analytics": 1,
    "monorepo": 1,
    "mysql": 1,
    "nest": 1,
    "nestjs": 1,
    "nextjs": 1,
    "ng-zorro": 1,
    "ngx": 1,
    "node": 1,
    "node-module": 1,
    "nodejs": 2,
    "nodejs-framework": 1,
    "nx": 1,
    "nx-workspaces": 1,
    "openapi": 1,
    "oracle": 1,
    "orm": 1,
    "pinpoint": 1,
    "postgresql": 1,
    "productivity": 1,
    "pwa": 2,
    "python": 1,
    "react": 7,
    "react-components": 1,
    "react-framework": 1,
    "react-native": 2,
    "react-spring": 1,
    "real-time": 1,
    "remote-work": 1,
    "rest": 1,
    "rich-text": 1,
    "rich-text-html-editor": 1,
    "sap": 1,
    "sap-hana": 1,
    "screenshot": 1,
    "spring": 1,
    "spring-physics": 1,
    "springs": 1,
    "sqlite": 1,
    "sqlserver": 1,
    "storage": 1,
    "storybook": 1,
    "streamlit": 1,
    "svg": 1,
    "swagger": 1,
    "terminal": 1,
    "terminal-emulators": 1,
    "testing": 1,
    "typeorm": 1,
    "typescript": 9,
    "typescript-framework": 1,
    "ui-components": 1,
    "umi": 1,
    "umijs": 1,
    "uml-diagram": 1,
    "visual-studio-code": 1,
    "vscode": 1,
    "vscode-extension": 1,
    "vscode-remote": 1,
    "wangeditor": 1,
    "web": 2,
    "web-framework": 1,
    "web-performance": 1,
    "websockets": 1,
    "websql": 1,
    "whiteboard": 1,
    "widgets": 1,
    "workflows": 1,
    "wysiwyg": 1,
    "wysiwyg-editor": 1
}
