{
    "3d-graphics": 1,
    "analytics": 1,
    "annotation": 1,
    "annotation-tool": 1,
    "annotations": 1,
    "apis": 1,
    "apollo": 1,
    "athena": 1,
    "automation": 1,
    "aws": 1,
    "badge": 1,
    "blog": 1,
    "book": 1,
    "boundingbox": 1,
    "browser": 1,
    "cartography": 1,
    "chart": 1,
    "ci-cd": 1,
    "cicd": 1,
    "cli": 1,
    "compiler": 2,
    "components": 1,
    "computer-vision": 1,
    "cube": 1,
    "cypress": 1,
    "cytoscape": 1,
    "data": 1,
    "data-flow": 1,
    "data-labeling": 1,
    "data-science": 1,
    "database": 1,
    "dataset": 1,
    "datasets": 2,
    "declarative": 1,
    "deep-learning": 1,
    "developer-tools": 1,
    "diagram": 1,
    "dnd": 1,
    "drag": 1,
    "drag-and-drop": 1,
    "e2e-testing": 1,
    "e2e-tests": 1,
    "electron": 1,
    "embeddable": 1,
    "embedded-database": 1,
    "end-to-end-testing": 1,
    "event-source": 1,
    "event-sources": 1,
    "event-sourcing": 1,
    "eventsourcing": 1,
    "eventstream": 1,
    "frontend": 1,
    "generator": 1,
    "gitbook": 1,
    "github": 1,
    "github-actions": 1,
    "gitlab-ci": 1,
    "graphql": 1,
    "hive": 1,
    "honkit": 1,
    "hybrid": 1,
    "image-annotation": 1,
    "image-classification": 1,
    "image-labeling": 1,
    "image-labelling-tool": 1,
    "imagenet": 1,
    "inputmask": 1,
    "integration-flow": 1,
    "integrations": 1,
    "ipaas": 1,
    "jamstack": 1,
    "javascript": 3,
    "javascript-tests": 1,
    "javascriptt": 1,
    "jqlite": 1,
    "jquery-plugin": 1,
    "json": 1,
    "label-studio": 1,
    "labeling": 1,
    "labeling-tool": 1,
    "lerna": 1,
    "library": 1,
    "localstorage": 1,
    "lodash": 1,
    "low-code": 1,
    "low-code-development-platform": 1,
    "machine-learning": 1,
    "maps": 1,
    "maskedinput": 1,
    "metadata": 1,
    "microservice": 1,
    "monorepo": 1,
    "mysql": 1,
    "nextjs": 2,
    "node": 1,
    "nodejs": 3,
    "npm": 1,
    "package": 1,
    "performance": 1,
    "plugin": 1,
    "postgresql": 1,
    "presto": 1,
    "prisma": 1,
    "publishing": 1,
    "react": 4,
    "realtime": 1,
    "redis-cluster": 1,
    "redis-desktop": 1,
    "redis-desktop-manager": 1,
    "redis-gui": 1,
    "reordering": 1,
    "security": 1,
    "semantic-segmentation": 1,
    "server-rendering": 1,
    "serverless": 1,
    "sortable": 1,
    "spark": 1,
    "speed": 1,
    "ssg": 1,
    "static": 1,
    "static-site-generation": 1,
    "static-site-generator": 1,
    "status": 1,
    "svg": 1,
    "template": 1,
    "test": 1,
    "test-automation": 1,
    "test-runner": 1,
    "test-suite": 1,
    "testing": 1,
    "testing-tools": 1,
    "tests": 1,
    "text-annotation": 1,
    "threejs": 1,
    "tilesets": 1,
    "toolbox": 1,
    "tooling": 1,
    "ui": 2,
    "universal": 1,
    "vanilla-javascript": 1,
    "vercel": 2,
    "webframework": 1,
    "webgl": 1,
    "workflow": 1,
    "workflows": 1,
    "yolo": 1,
    "zeit": 1
}
