{
    "adb": 1,
    "algorithm": 1,
    "algorithm-competitions": 1,
    "algorithms-implemented": 1,
    "algos": 1,
    "android": 1,
    "android-debug-bridge": 1,
    "android-device": 1,
    "android-exploit": 1,
    "android-hack": 1,
    "android-hacking": 1,
    "android-rat": 1,
    "ansi-colors": 1,
    "api": 1,
    "architecture": 1,
    "arxiv": 1,
    "async": 1,
    "asyncio": 1,
    "audio-processing": 1,
    "auditing": 1,
    "awesome": 1,
    "aws": 1,
    "azure": 1,
    "backdoor": 1,
    "bayesian": 1,
    "bert": 1,
    "book": 1,
    "cascade-rcnn": 1,
    "cli": 1,
    "cloud": 1,
    "community-driven": 1,
    "computer-vision": 1,
    "creating-deepfakes": 1,
    "darknet2pytorch": 1,
    "data-science": 1,
    "deep-face-swap": 2,
    "deep-learning": 6,
    "deep-neural-networks": 2,
    "deep-reinforcement-learning": 1,
    "deepface": 2,
    "deepfacelab": 1,
    "deepfakes": 2,
    "deeplearning": 2,
    "deezer": 1,
    "diagram": 1,
    "diagram-as-code": 1,
    "drawing": 1,
    "education": 1,
    "emoji": 1,
    "ensemble-learning": 1,
    "entynetproject": 1,
    "exploit": 1,
    "exploitation-framework": 1,
    "face-swap": 2,
    "faceswap": 2,
    "fakeapp": 2,
    "fast-rcnn": 1,
    "fastapi": 1,
    "faster-rcnn": 1,
    "framework": 1,
    "gcp": 1,
    "github": 1,
    "google": 1,
    "gpt": 1,
    "hack": 1,
    "hacking": 1,
    "hacking-tools": 1,
    "hellogithub": 1,
    "inference": 1,
    "information-gathering": 1,
    "instance-segmentation": 1,
    "interview": 1,
    "json": 1,
    "json-schema": 1,
    "kaggle": 1,
    "kali-linux": 1,
    "language-model": 1,
    "language-models": 1,
    "learn": 1,
    "linux": 1,
    "machine-learning": 3,
    "macos": 1,
    "markdown": 1,
    "mask-rcnn": 1,
    "model": 1,
    "mxnet": 1,
    "myfakeapp": 1,
    "natural-language-generation": 1,
    "natural-language-processing": 3,
    "natural-language-understanding": 2,
    "neural-nets": 2,
    "neural-networks": 3,
    "nlp": 2,
    "notebook": 1,
    "object-detection": 1,
    "onnx-model": 1,
    "openapi": 1,
    "openapi3": 1,
    "openfaceswap": 1,
    "osint": 1,
    "post-exploitation": 1,
    "practice": 1,
    "progress-bar": 1,
    "progress-bar-python": 1,
    "prototyping": 1,
    "pydantic": 1,
    "python": 7,
    "python-library": 1,
    "python-types": 1,
    "python3": 3,
    "pytorch": 4,
    "pytorch-transformers": 1,
    "pytorch-yolov4": 1,
    "rat": 1,
    "reconnaissance": 1,
    "redoc": 1,
    "redteam": 1,
    "regularization": 1,
    "reinforcement-learning": 1,
    "remote-access": 1,
    "remote-shell": 1,
    "rest": 1,
    "retinanet": 1,
    "rich": 1,
    "rpn": 1,
    "searches": 1,
    "security": 1,
    "sherlock": 1,
    "sorting-algorithms": 1,
    "sorts": 1,
    "ssd": 1,
    "starlette": 1,
    "swagger": 1,
    "swagger-ui": 1,
    "syntax-highlighting": 1,
    "tables": 1,
    "tensorflow": 3,
    "terminal": 1,
    "terminal-color": 1,
    "tools": 1,
    "traceback": 1,
    "tracebacks-rich": 1,
    "transformer-xl": 1,
    "unity": 1,
    "unity3d": 1,
    "uvicorn": 1,
    "web": 1,
    "windows": 1,
    "xgboost": 1,
    "xlm": 1,
    "xlnet": 1,
    "yolov4": 1
}
