{
    "activemq": 1,
    "activiti": 1,
    "amazon-web-services": 1,
    "android": 4,
    "animation": 1,
    "ant-design": 1,
    "ant-design-vue": 1,
    "antd": 1,
    "apache-kafka": 1,
    "api": 1,
    "api-client": 1,
    "api-server": 1,
    "aws-mobile": 1,
    "aws-sdk": 1,
    "aws-sdk-android": 1,
    "banner": 1,
    "bedrock": 1,
    "bedrock-edition": 1,
    "bedrock-to-java": 1,
    "breakpoint": 1,
    "bridge": 1,
    "cdc": 1,
    "change-data-capture": 1,
    "chart": 1,
    "codegenerator": 1,
    "config-management": 1,
    "configuration": 1,
    "configuration-management": 1,
    "database": 1,
    "debezium": 1,
    "distributed-configuration": 1,
    "distributed-search-engine": 1,
    "distributed-systems": 1,
    "doocs": 1,
    "download": 1,
    "downloader": 1,
    "dubbo": 2,
    "elasticsearch": 1,
    "eureka": 1,
    "event-streaming": 1,
    "feign": 1,
    "filedownloader": 1,
    "flowable": 1,
    "framework": 1,
    "generator": 1,
    "geyser": 1,
    "geysermc": 1,
    "graph": 1,
    "high-availability": 1,
    "high-concurrency": 2,
    "http": 1,
    "hutool": 1,
    "hystrix": 1,
    "indicator": 1,
    "iview": 1,
    "java": 8,
    "java-edition": 1,
    "jbpm": 1,
    "jeecg": 1,
    "jeecgboot": 1,
    "json": 1,
    "jvm": 1,
    "jwt": 1,
    "kafka": 2,
    "kafka-connect": 1,
    "kafka-producer": 1,
    "kotlin": 1,
    "leetcode": 2,
    "leetcode-c": 1,
    "leetcode-classification": 1,
    "leetcode-java": 2,
    "leetcode-solutions": 2,
    "message-queue": 1,
    "microservices": 1,
    "microservices-architecture": 1,
    "minecraft": 1,
    "mpandroidchart": 1,
    "multiple-process": 1,
    "multiple-thread": 1,
    "multitasking": 1,
    "mybatis": 1,
    "mybatis-plus": 1,
    "openapi": 1,
    "openapi-generator": 1,
    "openapi3": 1,
    "openjdk": 1,
    "orm": 1,
    "packet": 1,
    "pe": 1,
    "protocol": 1,
    "proxy": 1,
    "rabbitmq": 1,
    "redis": 1,
    "rest": 1,
    "rest-api": 1,
    "rest-client": 1,
    "restful-api": 1,
    "ribbon": 1,
    "rocketmq": 1,
    "rpc": 1,
    "sdk": 1,
    "shiro": 1,
    "spring": 1,
    "spring-boot": 4,
    "spring-cloud": 3,
    "spring-cloud-alibaba": 1,
    "spring-cloud-netflix": 1,
    "spring-mvc": 1,
    "springboot": 1,
    "springcloud": 1,
    "springcloud-config": 1,
    "swagger2": 1,
    "tool": 1,
    "translator": 1,
    "util": 1,
    "viewpager": 1,
    "viewpager2": 1,
    "vue": 1,
    "zookeeper": 1,
    "zuul": 1
}
