{
    "3d": 1,
    "3d-face": 1,
    "3dmm": 1,
    "ai": 1,
    "algorithm": 1,
    "algorithm-competitions": 1,
    "algorithms-implemented": 1,
    "algos": 1,
    "anemometer": 1,
    "anime": 1,
    "archery": 1,
    "attack": 1,
    "automation": 1,
    "awesome": 1,
    "baidu": 1,
    "binlog2sql": 1,
    "bomber": 1,
    "bombers": 1,
    "bombing": 1,
    "book": 1,
    "calls": 1,
    "censorship": 1,
    "collections": 1,
    "community-driven": 1,
    "computer-vision": 2,
    "crawl": 1,
    "data-masking": 1,
    "data-science": 2,
    "ddos": 1,
    "deep-learning": 6,
    "deeplearning": 1,
    "education": 1,
    "email-bomb": 1,
    "email-bomber": 2,
    "face-alignment": 1,
    "flood": 1,
    "gh-ost": 1,
    "hacking": 1,
    "hacking-tool": 1,
    "hentai": 1,
    "image-inpainting": 1,
    "inception": 1,
    "interview": 1,
    "jupyter-notebook": 1,
    "kaggle": 1,
    "kali-linux": 1,
    "kali-linux-hacking": 1,
    "kali-nethunter": 1,
    "kali-scripts": 1,
    "keras": 2,
    "learn": 1,
    "learning": 1,
    "learning-by-doing": 1,
    "learning-python": 2,
    "lyft": 1,
    "machine-learning": 3,
    "machinelearning": 1,
    "mpi": 1,
    "mxnet": 2,
    "mybatis": 1,
    "natural-language-processing": 1,
    "neural-network": 2,
    "neural-networks": 1,
    "nlp": 1,
    "nlp-machine-learning": 1,
    "notebook": 1,
    "numspy": 1,
    "numspy-bomber": 1,
    "practice": 1,
    "programming-language": 1,
    "python": 7,
    "python-exercises": 1,
    "python-framework": 1,
    "python-library": 1,
    "python-resources": 1,
    "python3": 4,
    "pytorch": 3,
    "searches": 1,
    "selenium": 1,
    "sip-killer": 1,
    "sms": 2,
    "sms-bomber": 2,
    "sms-bombing": 1,
    "sms-flooder": 1,
    "social-engeneering": 1,
    "social-engeneering-toolkit": 1,
    "sorting-algorithms": 1,
    "sorts": 1,
    "spam": 1,
    "spammer": 1,
    "spamming": 1,
    "spark": 1,
    "speech-recognition": 1,
    "spider": 1,
    "sql-audit": 1,
    "sql-query": 1,
    "tcp": 1,
    "teaching-materials": 1,
    "tensorflow": 4,
    "termux": 2,
    "tkinter": 1,
    "uber": 1,
    "udp": 1,
    "whatabomb": 1,
    "whatsapp-bomber": 1,
    "whatsappbomber": 1,
    "wxpython": 1
}
