{
    "actions": 1,
    "active-record": 1,
    "age-estimation": 1,
    "angular": 2,
    "api-gateway": 1,
    "apollo-client": 1,
    "apollographql": 1,
    "autocomplete": 1,
    "automation": 1,
    "aws": 2,
    "aws-cdk": 1,
    "aws-lambda": 1,
    "azure": 1,
    "bash": 1,
    "browser": 1,
    "certificate": 1,
    "chrome": 1,
    "cli": 1,
    "cloud": 1,
    "cloudfront": 1,
    "cockroachdb": 1,
    "compiler": 1,
    "covid-19": 1,
    "cypress": 1,
    "data-mapper": 1,
    "database": 1,
    "e2e-testing": 1,
    "easy": 1,
    "ecommerce": 1,
    "edge": 1,
    "editor": 1,
    "electron": 2,
    "emotion-recognition": 1,
    "expectation": 1,
    "face-detection": 1,
    "face-landmarks": 1,
    "face-recognition": 1,
    "facebook": 1,
    "fill": 1,
    "firebase": 1,
    "firefox": 1,
    "fish": 1,
    "framework": 3,
    "gender-recognition": 1,
    "golang": 1,
    "graphql": 1,
    "graphql-client": 1,
    "hacktoberfest": 1,
    "hap": 1,
    "homebridge": 1,
    "homekit": 1,
    "homekit-accessory-protocol": 1,
    "homekit-api": 1,
    "homekit-bridge": 1,
    "icon": 1,
    "icon-components": 1,
    "icons": 1,
    "immersive": 1,
    "iterm2": 1,
    "javascript": 12,
    "javascript-framework": 1,
    "js": 1,
    "lambda": 2,
    "lambdaatedge": 1,
    "macos": 1,
    "mariadb": 1,
    "material": 1,
    "material-components": 1,
    "material-design": 1,
    "material-theme": 1,
    "micro-frontend": 2,
    "micro-frontends": 1,
    "microapp": 1,
    "microfrontend": 1,
    "microfrontends": 1,
    "microservices": 2,
    "monorepo": 1,
    "multiple-themes": 1,
    "mysql": 1,
    "nest": 1,
    "nestjs": 1,
    "next": 1,
    "nextjs": 3,
    "node": 2,
    "nodejs": 4,
    "nodejs-framework": 1,
    "nx": 1,
    "nx-workspaces": 1,
    "openapi": 1,
    "oracle": 1,
    "orm": 1,
    "package-manager": 1,
    "painless": 1,
    "painless-javascript-testing": 1,
    "pass": 1,
    "playwright": 1,
    "postgres": 1,
    "postgresql": 2,
    "postgrest": 1,
    "pwa": 1,
    "python": 1,
    "react": 3,
    "react-native": 1,
    "realtime": 1,
    "rest": 1,
    "rich-text": 1,
    "sap": 1,
    "sap-hana": 1,
    "semantic": 1,
    "serverless": 2,
    "serverless-framework": 1,
    "serverless-stack": 1,
    "shell": 1,
    "siri": 1,
    "slate": 1,
    "snapshot": 1,
    "sqlite": 1,
    "sqlserver": 1,
    "sst": 1,
    "storybook": 1,
    "stroke": 1,
    "supabase": 1,
    "svg": 1,
    "svg-icon": 1,
    "swagger": 1,
    "template": 1,
    "tensorflow": 1,
    "tensorflowjs": 1,
    "terminal": 1,
    "testing": 2,
    "text-editor": 1,
    "tfjs": 1,
    "typeorm": 1,
    "typescript": 7,
    "typescript-framework": 1,
    "ui": 2,
    "ui-components": 1,
    "ui-design": 1,
    "ui-kit": 1,
    "vue": 1,
    "vue-component": 1,
    "vue-components": 1,
    "vue-material": 1,
    "vue-next": 1,
    "vue3": 1,
    "vuejs": 1,
    "vuejs3": 1,
    "vuetify": 1,
    "vuetifyjs": 1,
    "wallet": 1,
    "web": 2,
    "web-framework": 1,
    "web-performance": 1,
    "webcomponents": 1,
    "webkit": 1,
    "websockets": 2,
    "websql": 1,
    "yarn": 1,
    "zsh": 1
}
