{
    "airtable": 1,
    "android": 1,
    "annotation": 1,
    "annotation-tool": 1,
    "annotations": 1,
    "apis": 2,
    "automation": 1,
    "axios": 1,
    "blog": 1,
    "body-parser": 1,
    "boundingbox": 1,
    "browser": 1,
    "browser-extension": 1,
    "build-tools": 1,
    "canvas": 1,
    "cassandra": 1,
    "cli": 1,
    "compiler": 1,
    "components": 1,
    "computer-vision": 1,
    "crate-io": 1,
    "css": 3,
    "cypress": 1,
    "dash": 1,
    "data": 1,
    "data-analysis": 1,
    "data-flow": 1,
    "data-labeling": 1,
    "data-visualization": 1,
    "dataset": 1,
    "datasets": 2,
    "declarative": 1,
    "deep-learning": 1,
    "e2e-testing": 1,
    "e2e-tests": 1,
    "electron": 1,
    "end-to-end-testing": 1,
    "event-source": 1,
    "event-sources": 1,
    "event-sourcing": 1,
    "eventsourcing": 1,
    "eventstream": 1,
    "expressjs": 1,
    "facebook-instant-games": 1,
    "fe-interview": 1,
    "file-upload": 1,
    "flash": 1,
    "framework": 1,
    "front-end": 2,
    "frontend": 3,
    "frontend-interview": 1,
    "game-development": 1,
    "game-frameworks": 1,
    "gamedev": 1,
    "hiring": 1,
    "hiring-without-whiteboards": 1,
    "hls": 1,
    "html": 4,
    "html5": 1,
    "html5-audio": 1,
    "html5-game-development": 1,
    "html5-video": 1,
    "hybrid": 1,
    "image-annotation": 1,
    "image-classification": 1,
    "image-labeling": 1,
    "image-labelling-tool": 1,
    "imagenet": 1,
    "integration-flow": 1,
    "integrations": 1,
    "interview": 2,
    "interview-questions": 1,
    "ios": 1,
    "ipaas": 1,
    "javascript": 10,
    "javascript-tests": 1,
    "jobs": 1,
    "jquery": 1,
    "js": 2,
    "jsonwebtoken": 1,
    "label-studio": 1,
    "labeling": 1,
    "labeling-tool": 1,
    "library": 1,
    "linux": 1,
    "low-code": 1,
    "low-code-development-platform": 1,
    "macos": 1,
    "material": 1,
    "material-components": 1,
    "material-design": 1,
    "material-theme": 1,
    "mit": 1,
    "mobx": 1,
    "mongodb": 1,
    "mongoose": 1,
    "mysql": 1,
    "nextjs": 1,
    "node": 4,
    "nodejs": 3,
    "oas": 1,
    "openapi": 1,
    "openapi-specification": 1,
    "phaser": 1,
    "phaser-development": 1,
    "phaserjs": 1,
    "player": 1,
    "postgres": 1,
    "presto": 1,
    "pwa": 1,
    "quasar-framework": 1,
    "react": 6,
    "realtime": 1,
    "redux": 1,
    "rest": 1,
    "resume": 1,
    "runtime": 1,
    "sap-hana": 1,
    "semantic-segmentation": 1,
    "server-rendering": 1,
    "server-side-rendering": 1,
    "slack": 1,
    "sql-editor": 1,
    "sql-server": 1,
    "ssg": 1,
    "ssr": 1,
    "static": 1,
    "static-site-generation": 1,
    "static-site-generator": 1,
    "tech": 1,
    "test": 1,
    "test-automation": 1,
    "test-runner": 1,
    "test-suite": 1,
    "testing": 1,
    "testing-tools": 1,
    "tests": 1,
    "text-annotation": 1,
    "thunk-middleware": 1,
    "toolbox": 1,
    "tooling": 1,
    "ui": 1,
    "universal": 1,
    "vercel": 1,
    "vertica": 1,
    "video": 1,
    "videojs": 1,
    "vue": 3,
    "vue-component": 1,
    "vue-components": 1,
    "vue2": 1,
    "vuejs": 1,
    "vuejs2": 1,
    "webapi": 1,
    "webgl": 1,
    "whiteboard": 1,
    "wiki": 1,
    "windows": 1,
    "workflow": 1,
    "workflows": 1,
    "yolo": 1,
    "zeit": 1,
    "zero-configuration": 1
}
