{
    "admin": 1,
    "angular": 2,
    "api": 1,
    "arm": 1,
    "asp-net-core": 1,
    "asp-net-core-identity": 1,
    "aspnet": 1,
    "aspnet-core": 1,
    "aspnetcore": 1,
    "aspnetcore-mvc": 1,
    "aurelia": 1,
    "avalonia": 1,
    "azure": 1,
    "bot-framework": 1,
    "bots": 1,
    "browser": 1,
    "c-plus-plus": 1,
    "c-sharp": 3,
    "cefsharp": 1,
    "circuit-breaker": 1,
    "circuit-breaker-pattern": 1,
    "clean-architecture": 1,
    "closedxml": 1,
    "codegen": 1,
    "command-line": 1,
    "controls": 1,
    "cross-platform": 1,
    "csharp": 3,
    "cybersecurity": 1,
    "ddd": 1,
    "ddd-patterns": 1,
    "design": 1,
    "docker": 1,
    "documentation": 1,
    "dotnet": 6,
    "dotnet-core": 1,
    "dotnetcore": 1,
    "dragablz": 1,
    "excel": 1,
    "fault-handler": 1,
    "file-manager": 1,
    "files-uwp": 1,
    "fluent-design": 1,
    "framework": 1,
    "gui": 1,
    "identity": 1,
    "identityserver4": 2,
    "identityserver4-admin": 1,
    "identityserver4-adminui": 1,
    "interop": 1,
    "javascript": 1,
    "linux": 1,
    "luis": 1,
    "luis-ai": 1,
    "macos": 1,
    "markdown": 1,
    "material": 1,
    "material-design": 1,
    "microservices": 1,
    "microsoft": 2,
    "microsoft-azure-powershell": 1,
    "microsoft-congnitive-services": 1,
    "multi-platform": 1,
    "netcore": 2,
    "nswag": 1,
    "oauth2": 1,
    "openapi": 1,
    "openid-connect": 1,
    "openxml": 1,
    "pinvoke": 1,
    "powershell": 2,
    "qnamaker": 1,
    "resilience": 1,
    "resiliency-patterns": 1,
    "retry-strategies": 1,
    "roslyn": 1,
    "sample-code": 1,
    "sdk": 1,
    "security": 1,
    "shell": 1,
    "spa": 1,
    "static-site-generator": 1,
    "swagger": 1,
    "template": 1,
    "theme": 2,
    "transient-fault-handling": 1,
    "typescript": 2,
    "ui": 1,
    "user-interface": 1,
    "uwp": 1,
    "visual-basic": 1,
    "visual-studio": 1,
    "vsix": 1,
    "webapi": 1,
    "windows": 1,
    "windowscontainers": 1,
    "winforms": 1,
    "wpf": 3,
    "xamarin": 2,
    "xamarin-forms": 1,
    "xaml": 4,
    "xlsm": 1,
    "xlsx": 1,
    "yeoman": 1
}
