{
    "3d-photo": 1,
    "abp": 1,
    "accessibility": 1,
    "algorithm": 1,
    "algorithm-challenges": 1,
    "algorithms": 1,
    "algorithms-datastructures": 1,
    "algorithms-implemented": 1,
    "ant": 1,
    "ant-design": 1,
    "antd": 1,
    "antd-vue": 1,
    "architecture": 1,
    "aspnetcore": 1,
    "c": 1,
    "chineseocr": 1,
    "chinesetextdetection": 1,
    "chinesetextrecognition": 1,
    "clash": 1,
    "compiler": 1,
    "cpp": 1,
    "crnn": 1,
    "cross-platform": 2,
    "csharp": 1,
    "css": 3,
    "data-structures": 1,
    "database": 1,
    "db": 1,
    "design-systems": 1,
    "documentation": 1,
    "domain-driven-design": 1,
    "dotnet-core": 1,
    "dynamic": 1,
    "east": 1,
    "electron-app": 1,
    "enterprise": 1,
    "firebase-auth": 1,
    "firebase-realtime-database": 1,
    "firebase-storage": 1,
    "flutter": 2,
    "flutter-app": 2,
    "flutter-apps": 2,
    "flutter-demo": 1,
    "flutter-examples": 1,
    "flutter-material": 1,
    "flutter-ui": 1,
    "flutter-widget": 1,
    "font": 1,
    "fontawesome": 1,
    "framework": 2,
    "frontend": 1,
    "git": 1,
    "golang": 1,
    "icons": 1,
    "implementation": 1,
    "interview": 3,
    "interview-practice": 1,
    "interview-preparation": 1,
    "interview-questions": 2,
    "interviews": 1,
    "java": 2,
    "java8": 1,
    "javascript": 2,
    "jvm": 1,
    "laravel": 1,
    "laravel-boilerplate": 1,
    "leetcode": 1,
    "markdown": 1,
    "material-components": 1,
    "material-design": 1,
    "multi-tenancy": 1,
    "music-player": 1,
    "mysql": 1,
    "nodejs": 1,
    "novel-view-synthesis": 1,
    "ocr": 1,
    "ocrlite": 1,
    "open-source": 1,
    "operating-system": 1,
    "paddleocr": 1,
    "paper": 1,
    "php": 1,
    "profile-readme": 1,
    "react": 2,
    "react-components": 1,
    "readme-generator": 1,
    "redis": 1,
    "reference": 1,
    "rocket": 1,
    "rocketmq": 1,
    "rosetta": 1,
    "rust": 1,
    "search": 1,
    "serverless": 1,
    "social": 1,
    "social-app": 1,
    "sort": 1,
    "sorting-algorithms": 1,
    "star-net": 1,
    "stl": 1,
    "svg-icons": 1,
    "svg-sprites": 1,
    "system": 1,
    "template": 1,
    "textdetection": 1,
    "textrecognition": 1,
    "twitter": 1,
    "twitter-clone": 1,
    "ui": 2,
    "ui-components": 1,
    "ui-design": 1,
    "vue": 1,
    "vue-antd": 1,
    "vue-antd-ui": 1,
    "vuecomponent": 1,
    "vuejs2": 1,
    "wai-aria": 1,
    "web": 2,
    "web-development": 1,
    "web-framework": 1,
    "webfont": 1,
    "wiki": 2,
    "zookeeper": 1
}
