{
    "activemq": 1,
    "activiti": 1,
    "algorithms": 1,
    "alibaba": 1,
    "alibaba-middleware": 1,
    "alibaba-oss": 1,
    "aliyun": 1,
    "android": 1,
    "animation": 1,
    "ant-design": 1,
    "ant-design-vue": 1,
    "antd": 1,
    "apm": 1,
    "big-data": 2,
    "camel": 1,
    "circuit-breaker": 1,
    "cloud": 1,
    "cloud-native": 4,
    "codegenerator": 1,
    "cross-platform": 1,
    "css": 1,
    "dapper": 1,
    "data-stream": 1,
    "data-streaming": 1,
    "data-streams": 1,
    "demo": 1,
    "distributed-configuration": 1,
    "distributed-messaging": 1,
    "distributed-search-engine": 1,
    "distributed-systems": 1,
    "distributed-tracing": 1,
    "distributed-transaction": 1,
    "docker": 1,
    "doocs": 1,
    "dubbo": 4,
    "elasticsearch": 1,
    "element": 1,
    "enmasse": 1,
    "eureka": 1,
    "excel": 1,
    "feign": 2,
    "flink": 1,
    "framework": 1,
    "groovy": 1,
    "guava": 1,
    "high-availability": 1,
    "high-concurrency": 1,
    "html": 1,
    "http": 1,
    "hystrix": 1,
    "in-action": 1,
    "integration": 1,
    "interview": 1,
    "iot": 1,
    "iview": 1,
    "java": 16,
    "javascript": 1,
    "jbpm": 1,
    "json": 1,
    "jvm": 1,
    "jwt": 1,
    "jxl": 1,
    "kafka": 2,
    "kafka-connect": 1,
    "kafka-streams": 1,
    "kotlin": 2,
    "kubernetes": 2,
    "kubernetes-controller": 1,
    "kubernetes-operator": 1,
    "leetcode": 1,
    "leetcode-c": 1,
    "leetcode-java": 1,
    "leetcode-solutions": 1,
    "library": 1,
    "message-queue": 1,
    "messaging": 1,
    "metrics": 1,
    "microservices": 4,
    "microservices-architecture": 1,
    "monitoring": 1,
    "mybatis": 1,
    "mybatis-plus": 1,
    "mysql": 1,
    "nacos": 1,
    "netflix-eureka": 1,
    "netflix-hystrix": 1,
    "netflix-zuul": 1,
    "netflixoss": 1,
    "network-client": 1,
    "network-server": 1,
    "notes": 1,
    "observability": 1,
    "oom": 1,
    "openshift": 1,
    "osgi": 1,
    "poi": 2,
    "quartz": 1,
    "rabbitmq": 1,
    "redis": 3,
    "rest": 1,
    "rest-api": 1,
    "ribbon": 2,
    "rocketmq": 2,
    "rpc": 1,
    "sagacity-sqltoy": 1,
    "scala": 1,
    "service-discovery": 1,
    "service-mesh": 1,
    "service-registry": 1,
    "shiro": 1,
    "skywalking": 1,
    "source-code-analysis": 1,
    "spring": 7,
    "spring-boot": 6,
    "spring-boot-2": 1,
    "spring-boot-demo": 1,
    "spring-cloud": 5,
    "spring-cloud-alibaba": 2,
    "spring-cloud-core": 2,
    "springcloud": 1,
    "springcloud-config": 1,
    "sqltoy": 1,
    "sqltoy-orm": 1,
    "swagger2": 1,
    "swift": 1,
    "system": 1,
    "system-design": 1,
    "test": 1,
    "test-automation": 1,
    "vue": 1,
    "web": 1,
    "xkcoding": 1,
    "xls": 1,
    "xlsx": 1,
    "xml": 2,
    "zookeeper": 2,
    "zuul": 1
}
